src/iracing_client/__init__.py
src/iracing_client/auth.py
src/iracing_client/data/__init__.py
src/iracing_client/data/common.py
src/iracing_client/data/constants.py
src/iracing_client/data/league.py
src/iracing_client/data/member.py
src/iracing_client/trace.py
iracing_client-0.1.1.dist-info/LICENSE
iracing_client-0.1.1.dist-info/METADATA
iracing_client-0.1.1.dist-info/WHEEL
iracing_client-0.1.1.dist-info/RECORD
