Metadata-Version: 2.1
Name: iracing-client
Version: 0.1.1
Summary: 
Author: James Carter
Author-email: tegatai@gmail.com
Requires-Python: >=3.10,<4.0
Classifier: Programming Language :: Python :: 3
Classifier: Programming Language :: Python :: 3.10
Classifier: Programming Language :: Python :: 3.11
Requires-Dist: requests (>=2.31.0,<3.0.0)
